ons_utils/__init__.py
ons_utils/_typing.py
ons_utils/config/__init__.py
ons_utils/config/config.py
ons_utils/config/validation.py
ons_utils/decorators.py
ons_utils/factories.py
ons_utils/generic.py
ons_utils/pandas.py
ons_utils/pyspark/__init__.py
ons_utils/pyspark/concat.py
ons_utils/pyspark/general.py
ons_utils/pyspark/udfs.py
ons_utils/testing.py
ons_utils-0.1.1.dist-info/LICENSE
ons_utils-0.1.1.dist-info/WHEEL
ons_utils-0.1.1.dist-info/METADATA
ons_utils-0.1.1.dist-info/RECORD
